<beans xmlns="http://www.springframework.org/schema/beans" xmlns:task="http://www.springframework.org/schema/task"
    xmlns:xsi="http://www.w3.org/2001/XMLSchema-instance" xmlns:context="http://www.springframework.org/schema/context"
    xmlns:aop="http://www.springframework.org/schema/aop" xmlns:tx="http://www.springframework.org/schema/tx"
    xmlns:mvc="http://www.springframework.org/schema/mvc"

    xsi:schemaLocation="http://www.springframework.org/schema/beans
      http://www.springframework.org/schema/beans/spring-beans-4.0.xsd
      http://www.springframework.org/schema/context
      http://www.springframework.org/schema/context/spring-context-4.0.xsd
      http://www.springframework.org/schema/aop
      http://www.springframework.org/schema/aop/spring-aop-4.0.xsd
      http://www.springframework.org/schema/tx
      http://www.springframework.org/schema/tx/spring-tx-4.0.xsd
      http://www.springframework.org/schema/task
      http://www.springframework.org/schema/task/spring-task-4.0.xsd
      http://www.springframework.org/schema/mvc
      http://www.springframework.org/schema/mvc/spring-mvc-4.0.xsd
      ">

    <!-- <task:annotation-driven scheduler="myScheduler" /> <task:scheduler id="myScheduler" pool-size="10" /> -->
    <!-- 自动扫描并载入包 -->
    <context:component-scan base-package="cn.cerc.core" />
    <context:component-scan base-package="cn.cerc.db" />
    <context:component-scan base-package="cn.cerc.mis" />
    <context:component-scan base-package="cn.cerc.ui" />
    <context:component-scan base-package="cn.cerc.sample" />
     <!-- 启动 springmvc -->
    <mvc:default-servlet-handler />
    <!-- 开启注解 -->
    <mvc:annotation-driven />
    <context:annotation-config />
    <!-- 启动定时器 -->
    <task:annotation-driven />

    <bean id="FrmClientTest" class="cn.cerc.sample.forms.FrmClientTest" scope="prototype">
    </bean>
    <bean id="FrmScanProduct" class="cn.cerc.sample.forms.FrmScanProduct" scope="prototype">
    </bean>
    <bean id="ErpRegister" class="cn.cerc.sample.forms.FrmErpRegister" scope="prototype">
    </bean>
    <bean id="FrmJayunSample" class="cn.cerc.sample.forms.FrmJayunSample" scope="prototype">
    </bean>
    <bean id="FrmAcceptor" class="cn.cerc.sample.forms.FrmAcceptor" scope="prototype">
    </bean>
</beans>